Metadata-Version: 1.1
Name: mcgrading
Version: 0.0.0
Summary: Build to serve at UniAndes.
Home-page: http://github.com/jsbarbosa/mcgrading
Author: Juan Barbosa
Author-email: js.barbosa10@uniandes.edu.co
License: GPL
Keywords: example documentation tutorial
Platform: UNKNOWN
Classifier: Development Status :: 1 - Planning
Classifier: Topic :: Utilities
Classifier: License :: OSI Approved :: GNU General Public License (GPL)
